intentguard/__init__.py
intentguard/app/__init__.py
intentguard/app/inference_options.py
intentguard/app/inference_provider.py
intentguard/app/intentguard.py
intentguard/app/intentguard_options.py
intentguard/app/judgement_cache.py
intentguard/app/message.py
intentguard/app/prompt_factory.py
intentguard/domain/__init__.py
intentguard/domain/code_object.py
intentguard/domain/evaluation.py
intentguard/domain/judge.py
intentguard/domain/judgement_options.py
intentguard/infrastructure/.gitignore
intentguard/infrastructure/__init__.py
intentguard/infrastructure/fs_judgement_cache.py
intentguard/infrastructure/llamafile.py
intentguard/infrastructure/llamafile_prompt_factory.py
intentguard-2.1.0.dist-info/LICENSE
intentguard-2.1.0.dist-info/METADATA
intentguard-2.1.0.dist-info/WHEEL
intentguard-2.1.0.dist-info/RECORD
