Metadata-Version: 2.3
Name: intentguard
Version: 2.1.0
Summary: A Python library for verifying code properties using natural language assertions.
License: MIT
Keywords: testing,pytest,unittest,ai-testing,llm,code-verification,natural-language,test-automation,code-quality,language-models
Author: Kosma Dunikowski
Author-email: kosmadunikowski@gmail.com
Requires-Python: >=3.10,<4.0
Classifier: Intended Audience :: Developers
Classifier: License :: OSI Approved :: MIT License
Classifier: Programming Language :: Python :: 3
Classifier: Programming Language :: Python :: 3.10
Classifier: Programming Language :: Python :: 3.11
Classifier: Programming Language :: Python :: 3.12
Classifier: Programming Language :: Python :: 3.13
Classifier: Topic :: Software Development :: Quality Assurance
Classifier: Topic :: Software Development :: Testing
Project-URL: Homepage, https://github.com/kdunee/intentguard
